dpshdl/__init__.py
dpshdl/collate.py
dpshdl/dataloader.py
dpshdl/dataset.py
dpshdl/experiments.py
dpshdl/numpy.py
dpshdl/prefetcher.py
dpshdl/py.typed
dpshdl/testing.py
dpshdl/utils.py
dpshdl/impl/__init__.py
dpshdl/impl/mnist.py
dpshdl-0.0.21.dist-info/LICENSE
dpshdl-0.0.21.dist-info/METADATA
dpshdl-0.0.21.dist-info/WHEEL
dpshdl-0.0.21.dist-info/top_level.txt
dpshdl-0.0.21.dist-info/RECORD
