Metadata-Version: 2.1
Name: dpshdl
Version: 0.0.21
Summary: Framework-agnostic library for loading data
Home-page: https://github.com/dpshai/dpshdl
Author: Benjamin Bolte
Requires-Python: >=3.11
License-File: LICENSE
Requires-Dist: numpy
Requires-Dist: Pillow
Requires-Dist: requests
Provides-Extra: dev
Requires-Dist: black ; extra == 'dev'
Requires-Dist: darglint ; extra == 'dev'
Requires-Dist: mypy ; extra == 'dev'
Requires-Dist: pytest ; extra == 'dev'
Requires-Dist: ruff ; extra == 'dev'
Requires-Dist: types-Pillow ; extra == 'dev'
Requires-Dist: types-requests ; extra == 'dev'
